{
  "generated_at": "2026-04-07T04:45:11.945717+08:00",
  "total_titles_processed": 530,
  "failed_sources": [],
  "trends": [
    {
      "keyword_group": "A股 上证 深证",
      "match_count": 4,
      "titles": [
        {
          "title": "应声20CM涨停！A股一季报行情打响，12家上市公司净利最高同比预增超200%",
          "url": "https://www.cls.cn/detail/2335507",
          "source": "财联社热门",
          "ranks": [
            1
          ],
          "is_new": false,
          "appearance_count": 5,
          "time_info": "[00时55分 ~ 04时45分]"
        },
        {
          "title": "A股近期将有73.18亿股限售股解禁，总市值约1090.02亿元",
          "url": "https://m.thepaper.cn/newsDetail_forward_32911415",
          "source": "澎湃新闻",
          "ranks": [
            5
          ],
          "is_new": false,
          "appearance_count": 5,
          "time_info": "[00时55分 ~ 04时45分]"
        },
        {
          "title": "A股短期见底了吗？十大券商策略来了",
          "url": "https://www.cls.cn/detail/2335817",
          "source": "财联社热门",
          "ranks": [
            12,
            10
          ],
          "is_new": false,
          "appearance_count": 4,
          "time_info": "[01时51分 ~ 04时45分]"
        },
        {
          "title": "盘中创历史新高A股名单一览：长飞光纤、亨通光电等多只光纤概念股在列",
          "url": "https://www.cls.cn/detail/2335367",
          "source": "财联社热门",
          "ranks": [
            13
          ],
          "is_new": false,
          "appearance_count": 1,
          "time_info": "00时55分"
        }
      ]
    }
  ],
  "report_image_url": "https://ysyhope.github.io/TrendRadar/img/news.jpg"
}