{
  "generated_at": "2026-04-02T02:08:53.143551+08:00",
  "total_titles_processed": 373,
  "failed_sources": [],
  "trends": [
    {
      "keyword_group": "A股 上证 深证",
      "match_count": 2,
      "titles": [
        {
          "title": "170家A股公司收“罚单”20家被立案 一季度监管紧盯蹭热点炒概念",
          "url": "https://www.cls.cn/detail/2332482",
          "source": "财联社热门",
          "ranks": [
            9
          ],
          "is_new": false,
          "appearance_count": 3,
          "time_info": "[01时01分 ~ 02时08分]"
        },
        {
          "title": "【焦点复盘】A股放量普涨迎4月“开门红”，AI硬件、创新药概念强势领涨",
          "url": "https://www.cls.cn/detail/2332176",
          "source": "财联社热门",
          "ranks": [
            11
          ],
          "is_new": false,
          "appearance_count": 3,
          "time_info": "[01时01分 ~ 02时08分]"
        }
      ]
    }
  ],
  "report_image_url": "https://ysyhope.github.io/TrendRadar/img/news.jpg"
}